morse.py
setup.cfg
setup.py
morse.egg-info/PKG-INFO
morse.egg-info/SOURCES.txt
morse.egg-info/dependency_links.txt
morse.egg-info/top_level.txt