Metadata-Version: 1.0
Name: morse
Version: 1.0
Summary: Convert strings to morse code.
Home-page: UNKNOWN
Author: Augie Fackler <durin42@gmail.com>
Author-email: UNKNOWN
License: Apache License, Version 2.0
Platform: UNKNOWN
